setup.py
jania_probability/Binomialdistribution.py
jania_probability/Gaussiandistribution.py
jania_probability/Generaldistribution.py
jania_probability/__init__.py
jania_probability.egg-info/PKG-INFO
jania_probability.egg-info/SOURCES.txt
jania_probability.egg-info/dependency_links.txt
jania_probability.egg-info/not-zip-safe
jania_probability.egg-info/top_level.txt