Metadata-Version: 1.0
Name: jania-probability
Version: 0.1
Summary: Gaussian and Binomial distributions
Home-page: UNKNOWN
Author: Jania Mulanovich
Author-email: UNKNOWN
License: UNKNOWN
Platform: UNKNOWN
